fsspec_httpx/__init__.py
fsspec_httpx/filesystem.py
fsspec_httpx/py.typed
fsspec_httpx-0.1.4.dist-info/METADATA
fsspec_httpx-0.1.4.dist-info/WHEEL
fsspec_httpx-0.1.4.dist-info/licenses/LICENSE
fsspec_httpx-0.1.4.dist-info/RECORD
