Metadata-Version: 2.4
Name: fsspec-httpx
Version: 0.1.4
Summary: httpx-based fsspec filesystem
Project-URL: Documentation, https://phil65.github.io/fsspec-httpx/
Project-URL: Source, https://github.com/phil65/fsspec-httpx
Project-URL: Issues, https://github.com/phil65/fsspec-httpx/issues
Project-URL: Discussions, https://github.com/phil65/fsspec-httpx/discussions
Project-URL: Code coverage, https://app.codecov.io/gh/phil65/fsspec-httpx
Author-email: Philipp Temminghoff <philipptemminghoff@googlemail.com>
License: MIT License
License-File: LICENSE
Classifier: Development Status :: 4 - Beta
Classifier: Intended Audience :: Developers
Classifier: Operating System :: OS Independent
Classifier: Programming Language :: Python :: 3
Classifier: Programming Language :: Python :: 3 :: Only
Classifier: Programming Language :: Python :: 3.12
Classifier: Programming Language :: Python :: 3.13
Classifier: Programming Language :: Python :: 3.14
Classifier: Topic :: Documentation
Classifier: Topic :: Software Development
Classifier: Topic :: Utilities
Classifier: Typing :: Typed
Requires-Python: >=3.12
Requires-Dist: bs4>=0.0.2
Requires-Dist: fsspec>=2025.2.0
Requires-Dist: httpx>=0.28.1
Requires-Dist: universal-pathlib>=0.2.6
Requires-Dist: yarl
